nonebot_plugin_ac_demo/__init__.py
nonebot_plugin_ac_demo/matchers.py
nonebot_plugin_ac_demo/plugin_service.py
nonebot_plugin_rbac-0.0.1.dist-info/LICENSE
nonebot_plugin_rbac-0.0.1.dist-info/WHEEL
nonebot_plugin_rbac-0.0.1.dist-info/METADATA
nonebot_plugin_rbac-0.0.1.dist-info/RECORD
